tlxzoo/__init__.py
tlxzoo/version.py
tlxzoo/datasets/__init__.py
tlxzoo/datasets/data_loader.py
tlxzoo/datasets/dataset.py
tlxzoo/datasets/cifar10/__init__.py
tlxzoo/datasets/cifar10/cifar10.py
tlxzoo/datasets/circles/__init__.py
tlxzoo/datasets/circles/circles.py
tlxzoo/datasets/coco/__init__.py
tlxzoo/datasets/coco/coco.py
tlxzoo/datasets/conll2003/__init__.py
tlxzoo/datasets/conll2003/conll2003.py
tlxzoo/datasets/libri_speech/__init__.py
tlxzoo/datasets/libri_speech/libri_speech.py
tlxzoo/datasets/sst2/__init__.py
tlxzoo/datasets/sst2/sst2.py
tlxzoo/datasets/synth90k/__init__.py
tlxzoo/datasets/synth90k/synth90k.py
tlxzoo/datasets/wider/__init__.py
tlxzoo/datasets/wider/wider.py
tlxzoo/module/__init__.py
tlxzoo/module/arcface/__init__.py
tlxzoo/module/arcface/arcface.py
tlxzoo/module/bert/__init__.py
tlxzoo/module/bert/bert.py
tlxzoo/module/bert/transform.py
tlxzoo/module/detr/__init__.py
tlxzoo/module/detr/detr.py
tlxzoo/module/detr/modeling.py
tlxzoo/module/detr/transform.py
tlxzoo/module/detr/utils.py
tlxzoo/module/hrnet/__init__.py
tlxzoo/module/hrnet/hrnet.py
tlxzoo/module/hrnet/transform.py
tlxzoo/module/resnet/__init__.py
tlxzoo/module/resnet/resnet50.py
tlxzoo/module/retinaface/__init__.py
tlxzoo/module/retinaface/non_max_suppression.py
tlxzoo/module/retinaface/retinaface.py
tlxzoo/module/retinaface/transform.py
tlxzoo/module/t5/__init__.py
tlxzoo/module/t5/modeling.py
tlxzoo/module/t5/t5.py
tlxzoo/module/t5/transform.py
tlxzoo/module/trocr/__init__.py
tlxzoo/module/trocr/transform.py
tlxzoo/module/trocr/trocr.py
tlxzoo/module/trocr/trocr_decoder.py
tlxzoo/module/trocr/vit.py
tlxzoo/module/unet/__init__.py
tlxzoo/module/unet/unet.py
tlxzoo/module/vgg/__init__.py
tlxzoo/module/vgg/vgg.py
tlxzoo/module/wav2vec2/__init__.py
tlxzoo/module/wav2vec2/transform.py
tlxzoo/module/wav2vec2/wav2vec2.py
tlxzoo/module/yolo/__init__.py
tlxzoo/module/yolo/yolo.py
tlxzoo/speech/__init__.py
tlxzoo/speech/automatic_speech_recognition.py
tlxzoo/text/__init__.py
tlxzoo-0.0.1.dist-info/LICENSE
tlxzoo-0.0.1.dist-info/METADATA
tlxzoo-0.0.1.dist-info/WHEEL
tlxzoo-0.0.1.dist-info/top_level.txt
tlxzoo-0.0.1.dist-info/RECORD
