Metadata-Version: 2.1
Name: tlxzoo
Version: 0.0.1
Summary: zoo for tensorlayerx
Home-page: https://github.com/tensorlayer/TLXZoo
Author: tensorlayerx
Author-email: 
License: apache
Keywords: tensorlayerx zoo
Platform: UNKNOWN
Requires-Python: >=3.5
Requires-Dist: tensorlayerx (==0.5.1)
Requires-Dist: SoundFile
Requires-Dist: sentencepiece
Requires-Dist: sacrebleu
Requires-Dist: rouge-score
Requires-Dist: pycocotools
